portant/__init__.py
portant/decorators.py
portant/mixins.py
portant/commons/__init__.py
portant/commons/imaging.py
portant/commons/mixins.py
portant/commons/pdf.py
portant/commons/pricing.py
portant/commons/slugify.py
tests/__init__.py
tests/test_noop.py
portant_django_commons-1.0.10.dist-info/METADATA
portant_django_commons-1.0.10.dist-info/WHEEL
portant_django_commons-1.0.10.dist-info/top_level.txt
portant_django_commons-1.0.10.dist-info/RECORD
